ria/__init__.py
ria/_typing.py
ria/constants.py
ria/main.py
ria/callback/__init__.py
ria/callback/http_get_callback.py
python_ria-0.0.4.dist-info/LICENSE
python_ria-0.0.4.dist-info/METADATA
python_ria-0.0.4.dist-info/WHEEL
python_ria-0.0.4.dist-info/top_level.txt
python_ria-0.0.4.dist-info/RECORD
