Metadata-Version: 2.1
Name: python-ria
Version: 0.0.4
Author: Francisco Puig
Keywords: weather,RIA,Red de Información Agroclimática de Andalucía
Classifier: Programming Language :: Python :: 3.8
Classifier: Programming Language :: Python :: 3.9
Classifier: Programming Language :: Python :: 3.10
Classifier: License :: OSI Approved :: MIT License
Classifier: Operating System :: MacOS
Classifier: Operating System :: Microsoft
Classifier: Operating System :: POSIX :: Linux
Requires-Python: >=3.6
License-File: LICENSE
